protofuzz/__init__.py
protofuzz/gen.py
protofuzz/log.py
protofuzz/pbimport.py
protofuzz/protofuzz.py
protofuzz/values.py
protofuzz-0.2.dist-info/LICENSE
protofuzz-0.2.dist-info/METADATA
protofuzz-0.2.dist-info/WHEEL
protofuzz-0.2.dist-info/top_level.txt
protofuzz-0.2.dist-info/RECORD
