Metadata-Version: 2.1
Name: protofuzz
Version: 0.2
Summary: Google protobuf message generator
Home-page: https://github.com/trailofbits/protofuzz
Author: Trail of Bits
Author-email: UNKNOWN
License: MIT
Platform: UNKNOWN
Requires-Dist: protobuf (>=2.6.0)
